vectorshift/__init__.py
vectorshift/chatbot.py
vectorshift/knowledge_base.py
vectorshift/object.py
vectorshift/request.py
vectorshift/transformation.py
vectorshift/agent/__init__.py
vectorshift/agent/object.py
vectorshift/agent/tool.py
vectorshift/agent/tool_generator.py
vectorshift/agent/tools.py
vectorshift/integrations/__init__.py
vectorshift/integrations/integration.py
vectorshift/pipeline/__init__.py
vectorshift/pipeline/graph.py
vectorshift/pipeline/node.py
vectorshift/pipeline/node_generator.py
vectorshift/pipeline/nodes.py
vectorshift/pipeline/object.py
vectorshift-0.0.90.dist-info/METADATA
vectorshift-0.0.90.dist-info/WHEEL
vectorshift-0.0.90.dist-info/top_level.txt
vectorshift-0.0.90.dist-info/RECORD
