Metadata-Version: 2.4
Name: vectorshift
Version: 0.0.90
Summary: VectorShift Python SDK
Author: Alex Leonardi, Pratham Goyal, Eric Shen
Author-email: support@vectorshift.ai
Classifier: Programming Language :: Python :: 3
Requires-Dist: networkx==3.1
Requires-Dist: tomli>=2.0.1
Requires-Dist: pytest>=7.0.0
Requires-Dist: bson>=0.5.10
Requires-Dist: black>=23.0.0
Requires-Dist: pydantic>=2.0.0
Requires-Dist: aiohttp>=3.8.0
Dynamic: author
Dynamic: author-email
Dynamic: classifier
Dynamic: description
Dynamic: description-content-type
Dynamic: requires-dist
Dynamic: summary
